autopipe/__init__.py
autopipe/__main__.py
autopipe/autopipe.py
autopipe/logging.py
autopipe/models.py
autopipe/utils.py
autopipe/coordinators/__init__.py
autopipe/coordinators/download_example.py
autopipe/exceptions/ArgumentError.py
autopipe/exceptions/__init__.py
autopipe/input/__init__.py
autopipe/input/rss.py
autopipe/output/__init__.py
autopipe/pipe/__init__.py
autopipe/pipe/downloader.py
autopipe/pipe/filter_pipe.py
autopipe/pipe/tee.py
autopipe-0.0.3.data/scripts/autopipe
autopipe-0.0.3.dist-info/LICENSE
autopipe-0.0.3.dist-info/METADATA
autopipe-0.0.3.dist-info/WHEEL
autopipe-0.0.3.dist-info/top_level.txt
autopipe-0.0.3.dist-info/RECORD
