Metadata-Version: 2.1
Name: autopipe
Version: 0.0.3
Summary: A tool that allow one to create pipeline of automatic data processing.
Home-page: https://github.com/AnonymusRaccoon/Autopipe
Author: Zoe Roux
Author-email: zoe.roux@sdg.moe
License: UNKNOWN
Platform: UNKNOWN
Classifier: Programming Language :: Python :: 3
Classifier: License :: OSI Approved :: MIT License
Classifier: Operating System :: OS Independent
Requires-Python: >=3.6
Requires-Dist: requests
Requires-Dist: feedparser
